{
    "profiles": [
        {
            "complex_modifications": {
                "rules": [
                    {
                        "description": "Ctrl + Shift to Ctrl + Option + Space (rev 2)",
                        "manipulators": [
                            {
                                "from": {
                                    "key_code": "left_shift",
                                    "modifiers": { "mandatory": ["left_control"] }
                                },
                                "to": [
                                    {
                                        "key_code": "left_shift",
                                        "lazy": true,
                                        "modifiers": ["left_control"]
                                    }
                                ],
                                "to_if_alone": [
                                    {
                                        "key_code": "spacebar",
                                        "modifiers": ["left_control", "left_option"]
                                    }
                                ],
                                "type": "basic"
                            }
                        ]
                    }
                ]
            },
            "name": "Default profile",
            "selected": true,
            "simple_modifications": [
                {
                    "from": { "key_code": "left_control" },
                    "to": [{ "key_code": "left_command" }]
                },
                {
                    "from": { "key_code": "right_control" },
                    "to": [{ "key_code": "right_command" }]
                },
                {
                    "from": { "key_code": "left_command" },
                    "to": [{ "key_code": "left_control" }]
                },
                {
                    "from": { "key_code": "right_command" },
                    "to": [{ "key_code": "right_control" }]
                }
            ],
            "virtual_hid_keyboard": { "keyboard_type_v2": "ansi" }
        }
    ]
}